py_pypr/__init__.py
py_pypr/core.py
py_pypr/decos.py
py_pypr-0.1.0.dist-info/licenses/LICENSE
py_pypr-0.1.0.dist-info/METADATA
py_pypr-0.1.0.dist-info/WHEEL
py_pypr-0.1.0.dist-info/top_level.txt
py_pypr-0.1.0.dist-info/RECORD
