Metadata-Version: 2.4
Name: py-pypr
Version: 0.1.0
Summary: Py-Pypr is a pure Python library for functional shift operators.
Author: Burhan Qaddoumi
Maintainer: https://github.com/Burhan-Q
License: BSD 3-Clause License
Project-URL: homepage, https://github.com/Burhan-Q/py_pypr
Project-URL: source, https://github.com/Burhan-Q/py_pypr
Project-URL: issues, https://github.com/Burhan-Q/py_pypr/issues
Keywords: shift operators,python,pypr,pipelines,transformation
Requires-Python: >=3.11
License-File: LICENSE
Dynamic: license-file
